# Simple example which simulates a while loop.
DEF main
LOAD_CONST 10
LOAD_NAME counter
STORE
# This will be pc =  5
LOAD_CONST 0
LOAD_GLOBAL counter
LT
POP_JUMP_IF_FALSE 25
LOAD_GLOBAL counter
PRINT_ITEM
LOAD_GLOBAL counter
LOAD_CONST 1
MINUS
LOAD_NAME counter
STORE 
JUMP_ABSOLUTE 5
RETURN 0
ENDDEF

# >>> def bar():
# ...     counter = 10
# ...     while counter > 0:
# ...             print counter
# ...             counter -= 1
# ... 
# >>> bar()
# >>> dis.dis(bar)
#   2           0 LOAD_CONST               1 (10)
#               3 STORE_FAST               0 (counter)
# 
#   3           6 SETUP_LOOP              31 (to 40)
#         >>    9 LOAD_FAST                0 (counter)
#              12 LOAD_CONST               2 (0)
#              15 COMPARE_OP               4 (>)
#              18 POP_JUMP_IF_FALSE       39
# 
#   4          21 LOAD_FAST                0 (counter)
#              24 PRINT_ITEM          
#              25 PRINT_NEWLINE       
# 
#   5          26 LOAD_FAST                0 (counter)
#              29 LOAD_CONST               3 (1)
#              32 INPLACE_SUBTRACT    
#              33 STORE_FAST               0 (counter)
#              36 JUMP_ABSOLUTE            9
#         >>   39 POP_BLOCK           
#         >>   40 LOAD_CONST               0 (None)
#              43 RETURN_VALUE        


# 
# TEST_DATA
#
# expected = ProgramBox({ 'main' : CodeBox([OPCODES['LOAD_CONST'],
#                                           0,
#                                           OPCODES['LOAD_NAME'],
#                                           0,
#                                           OPCODES['STORE'],
#                                           OPCODES['LOAD_CONST'],
#                                           1,
#                                           OPCODES['LOAD_GLOBAL'],
#                                           1,
#                                           OPCODES['LT'],
#                                           OPCODES['POP_JUMP_IF_FALSE'],
#                                           2,
#                                           OPCODES['LOAD_GLOBAL'],
#                                           2,
#                                           OPCODES['PRINT_ITEM'],
#                                           OPCODES['LOAD_GLOBAL'],
#                                           3,
#                                           OPCODES['LOAD_CONST'],
#                                           3,
#                                           OPCODES['MINUS'],
#                                           OPCODES['LOAD_NAME'],
#                                           4,
#                                           OPCODES['STORE'],
#                                           OPCODES['JUMP_ABSOLUTE'],
#                                           4,
#                                           OPCODES['RETURN'],
#                                           5],
#                                          ['counter', 'counter',
#                                           'counter', 'counter',
#                                           'counter'],
#                                          [10, 0, 25, 1, 5, 0],
#                                          [])
#                         }
#                       )
# expected_stack = [0]
# expected_heap = {'counter' : 0}
#
# END_TEST_DATA
#